wgadmin/__init__.py
wgadmin/__main__.py
wgadmin/connection.py
wgadmin/main.py
wgadmin/network.py
wgadmin/peer.py
wgadmin/subcommands/__init__.py
wgadmin/subcommands/add_connection.py
wgadmin/subcommands/add_peer.py
wgadmin/subcommands/generate_all_configs.py
wgadmin/subcommands/generate_config.py
wgadmin/subcommands/list_peers.py
wgadmin/subcommands/new_network.py
wgadmin/templates/nm-connection
wgadmin/templates/wg-quick
wgadmin/util.py
wgadmin-0.2.0.dist-info/entry_points.txt
wgadmin-0.2.0.dist-info/LICENSE.txt
wgadmin-0.2.0.dist-info/WHEEL
wgadmin-0.2.0.dist-info/METADATA
wgadmin-0.2.0.dist-info/RECORD
