Metadata-Version: 2.1
Name: wgadmin
Version: 0.2.0
Summary: 
Home-page: https://github.com/f-koehler/wgadmin
License: GPL-3.0-only
Keywords: wireguard,vpn,network-manager
Author: Fabian Köhler
Author-email: fkoehler@physnet.uni-hamburg.de
Maintainer: Fabian Köhler
Maintainer-email: fkoehler@physnet.uni-hamburg.de
Requires-Python: >=3.8,<4.0
Classifier: Development Status :: 3 - Alpha
Classifier: Environment :: Console
Classifier: Intended Audience :: Developers
Classifier: Intended Audience :: End Users/Desktop
Classifier: Intended Audience :: System Administrators
Classifier: Intended Audience :: Telecommunications Industry
Classifier: License :: OSI Approved :: GNU General Public License v3 (GPLv3)
Classifier: Natural Language :: English
Classifier: Operating System :: OS Independent
Classifier: Programming Language :: Python :: 3
Classifier: Programming Language :: Python :: 3 :: Only
Classifier: Programming Language :: Python :: 3.8
Classifier: Topic :: Communications
Classifier: Topic :: Home Automation
Classifier: Topic :: Internet
Classifier: Topic :: Security
Classifier: Topic :: System
Classifier: Topic :: System :: Installation/Setup
Classifier: Topic :: System :: Networking
Classifier: Topic :: System :: Systems Administration
Classifier: Topic :: Utilities
Requires-Dist: argcomplete (==1.12.0)
Requires-Dist: jinja2 (==2.11.2)
Requires-Dist: pyyaml (==5.3.1)
Project-URL: Repository, https://github.com/f-koehler/wgadmin
